tests/__init__.py
tests/common.py
tests/common_comparers.py
tests/common_parallel.py
tests/common_systems.py
tests/conftest.py
tests/test_aux.py
tests/test_calc.py
tests/test_cluster.py
tests/test_create_w90_files.py
tests/test_data_k.py
tests/test_evaluate_k.py
tests/test_exceptions.py
tests/test_find_projections.py
tests/test_formatted.py
tests/test_path.py
tests/test_point_symmetry.py
tests/test_print.py
tests/test_projections.py
tests/test_run.py
tests/test_smoother.py
tests/test_sym_wann.py
tests/test_system.py
tests/test_tetra.py
tests/test_wannierise.py
wannierberri/__init__.py
wannierberri/evaluate_k.py
wannierberri/factors.py
wannierberri/io.py
wannierberri/models.py
wannierberri/parallel.py
wannierberri/run.py
wannierberri/smoother.py
wannierberri/utility.py
wannierberri/calculators/__init__.py
wannierberri/calculators/calculator.py
wannierberri/calculators/dynamic.py
wannierberri/calculators/sdct.py
wannierberri/calculators/static.py
wannierberri/calculators/tabulate.py
wannierberri/data_K/__init__.py
wannierberri/data_K/data_K.py
wannierberri/data_K/data_K_R.py
wannierberri/data_K/data_K_k.py
wannierberri/data_K/data_K_soc.py
wannierberri/data_K/sdct_K.py
wannierberri/formula/__init__.py
wannierberri/formula/covariant.py
wannierberri/formula/covariant_basic.py
wannierberri/formula/formula.py
wannierberri/fourier/__init__.py
wannierberri/fourier/fft.py
wannierberri/fourier/rvectors.py
wannierberri/grid/Kpoint.py
wannierberri/grid/Kpoint_tetra.py
wannierberri/grid/__init__.py
wannierberri/grid/grid.py
wannierberri/grid/grid_tetra.py
wannierberri/grid/path.py
wannierberri/grid/tetrahedron.py
wannierberri/result/__init__.py
wannierberri/result/energyresult.py
wannierberri/result/kbandresult.py
wannierberri/result/result.py
wannierberri/result/resultdict.py
wannierberri/result/tabresult.py
wannierberri/symmetry/Dwann.py
wannierberri/symmetry/__init__.py
wannierberri/symmetry/dmn.py
wannierberri/symmetry/orbitals.py
wannierberri/symmetry/point_symmetry.py
wannierberri-1.6.1.dist-info/licenses/LICENSE
wannierberri-1.6.1.dist-info/METADATA
wannierberri-1.6.1.dist-info/WHEEL
wannierberri-1.6.1.dist-info/top_level.txt
wannierberri-1.6.1.dist-info/RECORD
