Metadata-Version: 2.4
Name: wannierberri
Version: 1.6.1
Summary: Constructuion of Wannier functions and Wannier interpolation
Home-page: https://wannier-berri.org
Author: Stepan S. Tsirkin
Author-email: stepan.tsirkin@epfl.ch
Classifier: Programming Language :: Python :: 3
Classifier: License :: OSI Approved :: GNU General Public License v2 (GPLv2)
Classifier: Operating System :: OS Independent
Requires-Python: >=3.11
License-File: LICENSE
Requires-Dist: numpy>=2.0
Requires-Dist: scipy>=1.13
Requires-Dist: colorama
Requires-Dist: termcolor
Requires-Dist: numba>=0.55.2
Requires-Dist: packaging>=20.8
Requires-Dist: fortio>=0.4
Requires-Dist: wannier90io
Requires-Dist: xmltodict
Requires-Dist: matplotlib
Requires-Dist: sympy
Requires-Dist: spglib>=2
Requires-Dist: irrep>=2.4.1
Requires-Dist: spgrep
Provides-Extra: parallel
Requires-Dist: ray[default]; extra == "parallel"
Requires-Dist: protobuf==3.20.2; extra == "parallel"
Provides-Extra: fftw
Requires-Dist: pyFFTW>=0.12.0; extra == "fftw"
Provides-Extra: all
Requires-Dist: ray[default]; extra == "all"
Requires-Dist: protobuf==3.20.2; extra == "all"
Requires-Dist: pyFFTW>=0.12.0; extra == "all"
Provides-Extra: default
Requires-Dist: ray[default]; extra == "default"
Requires-Dist: protobuf==3.20.2; extra == "default"
Requires-Dist: ray[default]; extra == "default"
Requires-Dist: protobuf==3.20.2; extra == "default"
Requires-Dist: pyFFTW>=0.12.0; extra == "default"
Dynamic: author
Dynamic: author-email
Dynamic: classifier
Dynamic: description
Dynamic: description-content-type
Dynamic: home-page
Dynamic: license-file
Dynamic: provides-extra
Dynamic: requires-dist
Dynamic: requires-python
Dynamic: summary
